{"@@10":["@100: free","@101: free","@102: free","@103: free"],"@@20":["@200: Wellness Curriculum - 12:","@201: 3","@202: FH:","@203: Ms. Hanks:"],"@@21":["@210: free","@211: free","@212: free","@213: free"],"@@0":["@00: C English 4 Mystery &amp; Adv.:","@01: 1","@02: B112:","@03: Keaney:"],"@@1":["@10: free","@11: free","@12: free","@13: free"],"@@2":["@20: free","@21: free","@22: free","@23: free"],"@@3":["@30: free","@31: free","@32: free","@33: free"],"@@4":["@40: C English 4 Mystery &amp; Adv.:","@41: 1","@42: B112:","@43: Keaney:"],"@@5":["@50: free","@51: free","@52: free","@53: free"],"@@6":["@60: free","@61: free","@62: free","@63: free"],"@@19":["@190: Senior Seminar\/Buffa:","@191: 2","@192: B110:","@193: Buffa:"],"@@7":["@70: free","@71: free","@72: free","@73: free"],"@@8":["@80: free","@81: free","@82: free","@83: free"],"@@17":["@170: free","@171: free","@172: free","@173: free"],"@@9":["@90: free","@91: free","@92: free","@93: free"],"@@18":["@180: C English 4 Mystery &amp; Adv.:","@181: 1","@182: B112:","@183: Keaney:"],"@@15":["@150: C English 4 Mystery &amp; Adv.:","@151: 1","@152: B112:","@153: Keaney:"],"@@16":["@160: Wellness Curriculum - 12:","@161: 3","@162: FH:","@163: Ms. Hanks:"],"@@13":["@130: free","@131: free","@132: free","@133: free"],"@@14":["@140: free","@141: free","@142: free","@143: free"],"@@11":["@110: C English 4 Mystery &amp; Adv.:","@111: 1","@112: B112:","@113: Keaney:"],"@@12":["@120: free","@121: free","@122: free","@123: free"],"@@31":["@310: Honors Social Science:","@311: 8","@312: B238:","@313: E. Lehmann:"],"@@32":["@320: Honors Applied Computer Science:","@321: 6","@322: B144:","@323: Hopps:"],"@@30":["@300: Introductory Statistics:","@301: 7","@302: B142:","@303: Forsberg:"],"@@28":["@280: free","@281: free","@282: free","@283: free"],"@@29":["@290: Honors Applied Computer Science:","@291: 6","@292: B144:","@293: Hopps:"],"@@26":["@260: Introductory Statistics:","@261: 7","@262: B142:","@263: Forsberg:"],"@@27":["@270: Honors Social Science:","@271: 8","@272: B238:","@273: E. Lehmann:"],"@@24":["@240: Art 1:","@241: 5","@242: A140:","@243: Latimer:"],"@@25":["@250: Honors Applied Computer Science:","@251: 6","@252: B144:","@253: Hopps:"],"@@22":["@220: C English 4 Mystery &amp; Adv.:","@221: 1","@222: B112:","@223: Keaney:"],"@10":["100: free","101: free","102: free","103: free"],"@@23":["@230: free","@231: free","@232: free","@233: free"],"@11":["110: C English 4 Mystery &amp; Adv.:","111: Keaney:","112: B112:","113: 1"],"@@42":["@420: Art 1:","@421: 5","@422: A140:","@423: Latimer:"],"@12":["120: free","121: free","122: free","123: free"],"@@43":["@430: Honors Applied Computer Science:","@431: 6","@432: B144:","@433: Hopps:"],"@13":["130: free","131: free","132: free","133: free"],"@@40":["@400: Introductory Statistics:","@401: 7","@402: B142:","@403: Forsberg:"],"@14":["140: free","141: free","142: free","143: free"],"@@41":["@410: Honors Social Science:","@411: 8","@412: B238:","@413: E. Lehmann:"],"@15":["150: C English 4 Mystery &amp; Adv.:","151: Keaney:","152: B112:","153: 1"],"@16":["160: Wellness Curriculum - 12:","161: Ms. Hanks:","162: FH:","163: 3"],"@17":["170: free","171: free","172: free","173: free"],"@18":["180: C English 4 Mystery &amp; Adv.:","181: Keaney:","182: B112:","183: 1"],"@19":["190: Senior Seminar\/Buffa:","191: Buffa:","192: B110:","193: 2"],"@@39":["@390: Art 1:","@391: 5","@392: A140:","@393: Latimer:"],"@@37":["@370: Introductory Statistics:","@371: 7","@372: B142:","@373: Forsberg:"],"@@38":["@380: Honors Social Science:","@381: 8","@382: B238:","@383: E. Lehmann:"],"@@35":["@350: Art 1:","@351: 5","@352: A140:","@353: Latimer:"],"@@36":["@360: Honors Applied Computer Science:","@361: 6","@362: B144:","@363: Hopps:"],"@20":["200: Wellness Curriculum - 12:","201: Ms. Hanks:","202: FH:","203: 3"],"@@33":["@330: Introductory Statistics:","@331: 7","@332: B142:","@333: Forsberg:"],"@21":["210: free","211: free","212: free","213: free"],"@@34":["@340: Honors Social Science:","@341: 8","@342: B238:","@343: E. Lehmann:"],"@22":["220: C English 4 Mystery &amp; Adv.:","221: Keaney:","222: B112:","223: 1"],"@@53":["@530: Advisory:","@531: A","@532: B132:","@533: Forsberg:"],"@23":["230: free","231: free","232: free","233: free"],"@@54":["@540: Advisory:","@541: A","@542: B132:","@543: Forsberg:"],"@24":["240: Art 1:","241: Latimer:","242: A140:","243: 5"],"@@51":["@510: Advisory:","@511: A","@512: B132:","@513: Forsberg:"],"@25":["250: Honors Applied Computer Science:","251: Hopps:","252: B144:","253: 6"],"@@52":["@520: Advisory:","@521: A","@522: B132:","@523: Forsberg:"],"@26":["260: Introductory Statistics:","261: Forsberg:","262: B142:","263: 7"],"@27":["270: Honors Social Science:","271: E. Lehmann:","272: B238:","273: 8"],"@@50":["@500: Advisory:","@501: A","@502: B132:","@503: Forsberg:"],"@28":["280: free","281: free","282: free","283: free"],"@29":["290: Honors Applied Computer Science:","291: Hopps:","292: B144:","293: 6"],"@@48":["@480: Advisory:","@481: A","@482: B132:","@483: Forsberg:"],"@@49":["@490: Advisory:","@491: A","@492: B132:","@493: Forsberg:"],"@@46":["@460: Art 1:","@461: 5","@462: A140:","@463: Latimer:"],"@30":["300: Introductory Statistics:","301: Forsberg:","302: B142:","303: 7"],"@@47":["@470: Honors Applied Computer Science:","@471: 6","@472: B144:","@473: Hopps:"],"@31":["310: Honors Social Science:","311: E. Lehmann:","312: B238:","313: 8"],"@@44":["@440: Introductory Statistics:","@441: 7","@442: B142:","@443: Forsberg:"],"@32":["320: Honors Applied Computer Science:","321: Hopps:","322: B144:","323: 6"],"@@45":["@450: Honors Social Science:","@451: 8","@452: B238:","@453: E. Lehmann:"],"@33":["330: Introductory Statistics:","331: Forsberg:","332: B142:","333: 7"],"@34":["340: Honors Social Science:","341: E. Lehmann:","342: B238:","343: 8"],"@35":["350: Art 1:","351: Latimer:","352: A140:","353: 5"],"@36":["360: Honors Applied Computer Science:","361: Hopps:","362: B144:","363: 6"],"@37":["370: Introductory Statistics:","371: Forsberg:","372: B142:","373: 7"],"@38":["380: Honors Social Science:","381: E. Lehmann:","382: B238:","383: 8"],"@39":["390: Art 1:","391: Latimer:","392: A140:","393: 5"],"@40":["400: Introductory Statistics:","401: Forsberg:","402: B142:","403: 7"],"@41":["410: Honors Social Science:","411: E. Lehmann:","412: B238:","413: 8"],"@42":["420: Art 1:","421: Latimer:","422: A140:","423: 5"],"@@55":["@550: Advisory:","@551: A","@552: B132:","@553: Forsberg:"],"@43":["430: Honors Applied Computer Science:","431: Hopps:","432: B144:","433: 6"],"@44":["440: Introductory Statistics:","441: Forsberg:","442: B142:","443: 7"],"@45":["450: Honors Social Science:","451: E. Lehmann:","452: B238:","453: 8"],"@46":["460: Art 1:","461: Latimer:","462: A140:","463: 5"],"@47":["470: Honors Applied Computer Science:","471: Hopps:","472: B144:","473: 6"],"@48":["480: Advisory:","481: Forsberg:","482: B132:","483: A"],"@49":["490: Advisory:","491: Forsberg:","492: B132:","493: A"],"@50":["500: Advisory:","501: Forsberg:","502: B132:","503: A"],"@51":["510: Advisory:","511: Forsberg:","512: B132:","513: A"],"@52":["520: Advisory:","521: Forsberg:","522: B132:","523: A"],"@53":["530: Advisory:","531: Forsberg:","532: B132:","533: A"],"@54":["540: Advisory:","541: Forsberg:","542: B132:","543: A"],"@55":["550: Advisory:","551: Forsberg:","552: B132:","553: A"],"@0":["00: C English 4 Mystery &amp; Adv.:","01: Keaney:","02: B112:","03: 1"],"@1":["10: free","11: free","12: free","13: free"],"@2":["20: free","21: free","22: free","23: free"],"@3":["30: free","31: free","32: free","33: free"],"@4":["40: C English 4 Mystery &amp; Adv.:","41: Keaney:","42: B112:","43: 1"],"@5":["50: free","51: free","52: free","53: free"],"@6":["60: free","61: free","62: free","63: free"],"@7":["70: free","71: free","72: free","73: free"],"@8":["80: free","81: free","82: free","83: free"],"@9":["90: free","91: free","92: free","93: free"]}